grist/__init__.py
grist-0.1.0.dev0.dist-info/WHEEL
grist-0.1.0.dev0.dist-info/entry_points.txt
grist-0.1.0.dev0.dist-info/METADATA
grist-0.1.0.dev0.dist-info/RECORD
