Metadata-Version: 2.3
Name: grist
Version: 0.1.0.dev0
Summary: Generative Retrieval Id Semantic Transforms on top of Google Grain.
Author: chicham
Author-email: chicham <hicham.randrianarivo@artefact.com>
Requires-Python: >=3.10, <3.13
